dynamicWebsite.py
dynamicWebsite-1.4.4.dist-info/METADATA
dynamicWebsite-1.4.4.dist-info/WHEEL
dynamicWebsite-1.4.4.dist-info/top_level.txt
dynamicWebsite-1.4.4.dist-info/RECORD
