Metadata-Version: 2.1
Name: dynamicWebsite
Version: 1.4.4
Summary: A simple way to host web server bundled with websocket to send and receive live data, from client to server, and pass live HTML changes from server to client without having to refresh the page.
Author-email: Bhindi <bhaskarpanja93@gmail.com>, riyapuri0710 <riyapuri0710@gmail.com>
Project-URL: Homepage, https://github.com/BhaskarPanja93/dynamicWebsite
Keywords: website,dynamic website,update website,live website,change website,websocket
Classifier: License :: OSI Approved :: MIT License
Classifier: Programming Language :: Python
Classifier: Programming Language :: Python :: 3
Requires-Python: >=3.6
Requires-Dist: randomisedString
Requires-Dist: cryptography
Requires-Dist: Flask
Requires-Dist: flask_sock
Requires-Dist: turbo_flask
Requires-Dist: rateLimitedQueues
